spax/__init__.py
spax/config.py
spax/dependency_graph.py
spax/distributions.py
spax/spaces/__init__.py
spax/spaces/base.py
spax/spaces/categorical.py
spax/spaces/conditional.py
spax/spaces/conditions.py
spax/spaces/numeric.py
spax-0.1.2a0.dist-info/licenses/LICENSE
spax-0.1.2a0.dist-info/METADATA
spax-0.1.2a0.dist-info/WHEEL
spax-0.1.2a0.dist-info/top_level.txt
spax-0.1.2a0.dist-info/RECORD
