Metadata-Version: 2.4
Name: spax
Version: 0.1.2a0
Summary: Declarative search space definition library for ML hyperparameter optimization
Author-email: Keyhan Kamyar <keyhankamyar@gmail.com>
Maintainer-email: Keyhan Kamyar <keyhankamyar@gmail.com>
License: MIT
Project-URL: Homepage, https://github.com/keyhankamyar/SpaX
Project-URL: Documentation, https://github.com/keyhankamyar/SpaX#readme
Project-URL: Repository, https://github.com/keyhankamyar/SpaX
Project-URL: Bug Tracker, https://github.com/keyhankamyar/SpaX/issues
Project-URL: Changelog, https://github.com/keyhankamyar/SpaX/releases
Keywords: hyperparameter-optimization,machine-learning,deep-learning,hyperparameter-tuning,experiment-tracking,search-space,automl,hpo,neural-architecture-search
Classifier: Development Status :: 3 - Alpha
Classifier: Intended Audience :: Developers
Classifier: Intended Audience :: Science/Research
Classifier: License :: OSI Approved :: MIT License
Classifier: Operating System :: OS Independent
Classifier: Programming Language :: Python :: 3
Classifier: Programming Language :: Python :: 3.10
Classifier: Programming Language :: Python :: 3.11
Classifier: Programming Language :: Python :: 3.12
Classifier: Topic :: Scientific/Engineering :: Artificial Intelligence
Classifier: Topic :: Software Development :: Libraries :: Python Modules
Classifier: Typing :: Typed
Requires-Python: >=3.11
License-File: LICENSE
Requires-Dist: pydantic<3.0.0,>=2.0.0
Provides-Extra: dev
Requires-Dist: pytest>=7.4.0; extra == "dev"
Requires-Dist: pytest-cov>=4.1.0; extra == "dev"
Requires-Dist: black>=23.0.0; extra == "dev"
Requires-Dist: ruff>=0.1.0; extra == "dev"
Requires-Dist: mypy>=1.5.0; extra == "dev"
Requires-Dist: pre-commit>=3.4.0; extra == "dev"
Provides-Extra: docs
Requires-Dist: mkdocs>=1.5.0; extra == "docs"
Requires-Dist: mkdocs-material>=9.4.0; extra == "docs"
Requires-Dist: mkdocstrings[python]>=0.23.0; extra == "docs"
Provides-Extra: visualization
Requires-Dist: matplotlib>=3.7.0; extra == "visualization"
Requires-Dist: seaborn>=0.12.0; extra == "visualization"
Requires-Dist: plotly>=5.17.0; extra == "visualization"
Provides-Extra: all
Requires-Dist: spax[dev,docs,visualization]; extra == "all"
Dynamic: license-file
